tests/__init__.py
tests/test_wallet.py
digiffer_wallets_dev-1.0.0.dist-info/METADATA
digiffer_wallets_dev-1.0.0.dist-info/WHEEL
digiffer_wallets_dev-1.0.0.dist-info/entry_points.txt
digiffer_wallets_dev-1.0.0.dist-info/top_level.txt
digiffer_wallets_dev-1.0.0.dist-info/RECORD
