Metadata-Version: 2.1
Name: digiffer-wallets-dev
Version: 1.0.0
Summary: A Python package to interact with Digiffer Wallets API.
Home-page: UNKNOWN
Author: Your Name
Author-email: your.email@example.com
License: MIT
Platform: UNKNOWN
Classifier: Programming Language :: Python :: 3
Classifier: License :: OSI Approved :: MIT License
Classifier: Operating System :: OS Independent
Requires-Python: >=3.6
Requires-Dist: requests
Provides-Extra: test
Requires-Dist: unittest ; extra == 'test'
